<?xml version="1.0" encoding="utf-8"?>
<executable>
  <category></category>
  <title>Warp Volume</title>

<description>
</description>
  <version>0.1.0.$Revision: 8595 $(alpha)</version>
  <documentation-url>http://www.slicer.org/slicerWiki/index.php/Modules:</documentation-url>
  <license></license>
  <contributor></contributor>
<acknowledgements>
</acknowledgements>


<parameters>
    <label>Input/Output</label>
    <description>Input/Output Parameters</description>
     <image type="any">
        <name>input_image</name>
        <label>Input Image</label>
        <channel>input</channel>
        <longflag>--input</longflag>
        <description>Image to be resampled or warped</description>
      </image>
     <image type="any">
        <name>warp</name>
        <label>Warp Image</label>
        <channel>input</channel>
        <longflag>--warp</longflag>
        <description>If warping, this specifies deformation field to use</description>
      </image>
    <image type="any">
       <name>output_image</name>
       <label>Output Image</label>
       <channel>output</channel>
       <longflag>--output</longflag>
       <description>Resampled and/or warped image</description>
    </image>
    <boolean>                                                                                                                                                                                                                              
      <name>resample</name>
      <label>Resample DWI gradient directions?</label>
      <longflag>--resample</longflag>
      <description>Resamples the DWI to have a set of canonical gradient directions</description>
      <default>false</default>
    </boolean>
   <boolean>                                                                                                                                                                                                                              
      <name>resample_self</name>
      <label>Resample DWI at its own gradient directions?</label>
      <longflag>--resample_self</longflag>
      <description>Resamples the DWI at its own gradient directions</description>
      <default>false</default>
    </boolean>
   <boolean>                                                                                                                                                                                                                              
      <name>without_baselines</name>
      <label>Save output image without the baselines?</label>
      <longflag>--without_baselines</longflag>
      <description>If resampling, this flag will prevent the baselines from being written to the output image</description>
      <default>false</default>
    </boolean>

</parameters>

</executable>
